fluent_formatter/__init__.py
python_fluent_log_formatter-1.0.0.dist-info/LICENSE
python_fluent_log_formatter-1.0.0.dist-info/METADATA
python_fluent_log_formatter-1.0.0.dist-info/WHEEL
python_fluent_log_formatter-1.0.0.dist-info/top_level.txt
python_fluent_log_formatter-1.0.0.dist-info/RECORD
